zc_podcastmaker_common/__init__.py
zc_podcastmaker_common/config_manager.py
zc_podcastmaker_common/errors.py
zc_podcastmaker_common/generative_llm_client.py
zc_podcastmaker_common/logging.py
zc_podcastmaker_common/message_bus_client.py
zc_podcastmaker_common/models.py
zc_podcastmaker_common/object_storage_client.py
zc_podcastmaker_common-0.1.0.dist-info/METADATA
zc_podcastmaker_common-0.1.0.dist-info/WHEEL
zc_podcastmaker_common-0.1.0.dist-info/RECORD
