Metadata-Version: 2.4
Name: zc-podcastmaker-common
Version: 0.1.0
Summary: Common utilities library for PodcastMaker components
Author-email: ZCZoft <info@zczoft.com>
Requires-Python: >=3.10
Requires-Dist: anthropic>=0.5.0
Requires-Dist: boto3>=1.28.0
Requires-Dist: pika>=1.3.0
Requires-Dist: pydantic>=2.0.0
Provides-Extra: dev
Requires-Dist: mypy>=1.0.0; extra == 'dev'
Requires-Dist: pytest-mock>=3.10.0; extra == 'dev'
Requires-Dist: pytest>=7.0.0; extra == 'dev'
Requires-Dist: ruff>=0.4.0; extra == 'dev'
